libizd/__init__.py
libizd/libioqt_snap.py
libizd/libizd.py
libizd/libizdgui.py
izd-1.0.1.dist-info/METADATA
izd-1.0.1.dist-info/WHEEL
izd-1.0.1.dist-info/licenses/LICENSE
izd-1.0.1.dist-info/RECORD
