Metadata-Version: 2.1
Name: izd
Version: 1.0.1
Summary: The IZD (io-zipped-doc) file format + tools (GUI, command-line creator, etc.).
Project-URL: Homepage, https://gitlab.com/vtopan/izd
Author-email: Vlad Topan <vtopan@gmail.removethispart.com>
License: MIT License
License-File: LICENSE
Classifier: License :: OSI Approved :: MIT License
Classifier: Programming Language :: Python
Classifier: Programming Language :: Python :: 3
Requires-Python: >=3.9
